datasette_backup/__init__.py
datasette_backup-0.1.dist-info/METADATA
datasette_backup-0.1.dist-info/WHEEL
datasette_backup-0.1.dist-info/entry_points.txt
datasette_backup-0.1.dist-info/top_level.txt
datasette_backup-0.1.dist-info/RECORD
