Metadata-Version: 2.1
Name: datasette-backup
Version: 0.1
Summary: Plugin adding backup options to Datasette
Home-page: https://github.com/simonw/datasette-backup
Author: Simon Willison
License: Apache License, Version 2.0
Project-URL: Issues, https://github.com/simonw/datasette-backup/issues
Project-URL: CI, https://github.com/simonw/datasette-backup/actions
Project-URL: Changelog, https://github.com/simonw/datasette-backup/releases
Platform: UNKNOWN
Requires-Dist: datasette
Requires-Dist: sqlite-dump (>=0.1.1)
Provides-Extra: test
Requires-Dist: pytest ; extra == 'test'
Requires-Dist: pytest-asyncio ; extra == 'test'
Requires-Dist: httpx ; extra == 'test'
Requires-Dist: sqlite-utils ; extra == 'test'
